ac-stubs/__init__.py
ac-stubs/info_identifier.py
ac_stubs-0.4.2.dist-info/LICENSE
ac_stubs-0.4.2.dist-info/METADATA
ac_stubs-0.4.2.dist-info/WHEEL
ac_stubs-0.4.2.dist-info/top_level.txt
ac_stubs-0.4.2.dist-info/RECORD
